mkapi/__init__.py
mkapi/main.py
mkapi/utils.py
mkapi/core/__init__.py
mkapi/core/attribute.py
mkapi/core/base.py
mkapi/core/code.py
mkapi/core/docstring.py
mkapi/core/inherit.py
mkapi/core/linker.py
mkapi/core/module.py
mkapi/core/node.py
mkapi/core/object.py
mkapi/core/page.py
mkapi/core/postprocess.py
mkapi/core/preprocess.py
mkapi/core/regex.py
mkapi/core/renderer.py
mkapi/core/signature.py
mkapi/core/structure.py
mkapi/plugins/__init__.py
mkapi/plugins/api.py
mkapi/plugins/mkdocs.py
mkapi/templates/bases.jinja2
mkapi/templates/code.jinja2
mkapi/templates/docstring.jinja2
mkapi/templates/items.jinja2
mkapi/templates/macros.jinja2
mkapi/templates/member.jinja2
mkapi/templates/module.jinja2
mkapi/templates/node.jinja2
mkapi/templates/object.jinja2
mkapi/theme/mkapi.yml
mkapi/theme/css/mkapi-common.css
mkapi/theme/css/mkapi-ivory.css
mkapi/theme/css/mkapi-mkdocs.css
mkapi/theme/css/mkapi-readthedocs.css
mkapi/theme/js/mkapi.js
mkapi_fix-0.1.1.dist-info/LICENSE
mkapi_fix-0.1.1.dist-info/METADATA
mkapi_fix-0.1.1.dist-info/WHEEL
mkapi_fix-0.1.1.dist-info/entry_points.txt
mkapi_fix-0.1.1.dist-info/top_level.txt
mkapi_fix-0.1.1.dist-info/RECORD
