Metadata-Version: 2.1
Name: mkapi-fix
Version: 0.1.1
Summary: An Auto API Documentation tool.
Home-page: https://github.com/pwwang/mkapi
Author: pwwang
Author-email: pwwang@pwwang.com
License: MIT
Classifier: Development Status :: 4 - Beta
Classifier: License :: OSI Approved :: MIT License
Classifier: Operating System :: OS Independent
Classifier: Programming Language :: Python
Classifier: Programming Language :: Python :: 3
Classifier: Programming Language :: Python :: 3.7
Classifier: Programming Language :: Python :: 3.8
Classifier: Topic :: Documentation
Requires-Python: >=3.7
License-File: LICENSE
Requires-Dist: markdown
Requires-Dist: jinja2
